custom_remote_user/__init__.py
custom_remote_user/backends.py
django_custom_remote_user-0.3.dist-info/METADATA
django_custom_remote_user-0.3.dist-info/RECORD
django_custom_remote_user-0.3.dist-info/WHEEL
django_custom_remote_user-0.3.dist-info/top_level.txt
