Metadata-Version: 2.1
Name: django-custom-remote-user
Version: 0.3
Summary: A simple Django app to enable custom behavior for remote user authentication
Home-page: https://github.com/HassanKadhem/django-custom-remote-user
Author: Hassan Kadhem
Author-email: hassan.kadhem@gmail.com
License: MIT License
Platform: UNKNOWN
Classifier: Environment :: Web Environment
Classifier: Framework :: Django
Classifier: Framework :: Django :: 1.10
Classifier: Intended Audience :: Developers
Classifier: License :: OSI Approved :: MIT License
Classifier: Operating System :: OS Independent
Classifier: Programming Language :: Python
Classifier: Programming Language :: Python :: 3.4
Classifier: Programming Language :: Python :: 3.6
Classifier: Topic :: Internet :: WWW/HTTP
Classifier: Topic :: Internet :: WWW/HTTP :: Dynamic Content
